{
    "name": "FieldError",
    "displayName": "FieldError",
    "description": "Error message for Field validation. Renders a `<div>` element.",
    "props": [
        {
            "name": "render",
            "type": ["ReactElement", "(props: HTMLProps) => ReactElement"],
            "required": false,
            "description": "Allows you to replace the component’s HTML element\nwith a different tag, or compose it with another component.\n\nAccepts a `ReactElement` or a function that returns the element to render."
        },
        {
            "name": "match",
            "type": [
                "\"badInput\"",
                "\"customError\"",
                "\"patternMismatch\"",
                "\"rangeOverflow\"",
                "\"rangeUnderflow\"",
                "\"stepMismatch\"",
                "\"tooLong\"",
                "\"tooShort\"",
                "\"typeMismatch\"",
                "\"valueMissing\"",
                "boolean"
            ],
            "required": false,
            "description": "Determines when to show the error message. Can be a boolean or a validity state key."
        }
    ]
}
